CHANGELOG.txt
LICENSE.txt
MANIFEST.in
README.md
setup.py
topsis/__init__.py
topsis/topsis.py
topsis_7016.egg-info/PKG-INFO
topsis_7016.egg-info/SOURCES.txt
topsis_7016.egg-info/dependency_links.txt
topsis_7016.egg-info/entry_points.txt
topsis_7016.egg-info/requires.txt
topsis_7016.egg-info/top_level.txt