Metadata-Version: 2.1
Name: topsis-7016
Version: 1.1.0
Summary: topsis package for MCDM problems
Home-page: UNKNOWN
Author: Mukul Sharda
Author-email: mukulsharda5@gmail.com
License: UNKNOWN
Keywords: topsis
Platform: UNKNOWN
Classifier: Programming Language :: Python :: 3
Classifier: Programming Language :: Python :: 3.6
Classifier: Programming Language :: Python :: 3.7
Classifier: License :: OSI Approved :: MIT License
Classifier: Operating System :: OS Independent
Requires-Python: >=3.6
License-File: LICENSE.txt
